{
    "accounts": [
        {
            "Email": "asdfg",
            "Number": "32343",
            "Pass": "12345678",
            "User": "alireza",
            "day": 256,
            "month": 512,
            "year": 1024
        },
        {
            "Email": "1",
            "Number": "1",
            "Pass": "1",
            "User": "mmd",
            "day": 256,
            "month": 512,
            "year": 1024
        },
        {
            "Email": "1",
            "Number": "1",
            "Pass": "1",
            "User": "nnd",
            "day": 256,
            "month": 512,
            "year": 1024
        }
    ]
}
